{
  "general": {
    "count_places": "{count} {count, plural, one {place} other {places}}",
    "order_by": {
      "updated_at": "Newest",
      "popularity_score": "Most popular",
      "activity_score": "Most active"
    },
    "place_share": "Look at this place I found in Decentraland: "
  },
  "navigation": {
    "overview": "Overview",
    "places": "Places",
    "my_places": "My Places"
  },
  "components": {
    "button": {
      "jump_in": "jump in",
      "favorite": "favorite",
      "share": "share",
      "join": "join"
    },
    "place_starts": {
      "active": "active",
      "favorites": "favorites",
      "visits": "visits",
      "created": "created",
      "updated": "updated",
      "point_of_interest": "point of interest",
      "favorite": "favorite"
    },
    "place_description": {
      "created_by": "created by",
      "description": "description",
      "location": "location"
    },
    "place_realm_activity": {
      "title": "realms",
      "realm": "realm",
      "players": "players"
    },
    "overview_list": {
      "view_all": "view all"
    }
  },
  "pages": {
    "overview": {
      "title": "Places",
      "search_the_metaverse": "Search the Metaverse",
      "popular": "Popular",
      "Featured": "Featured",
      "my_favorites": "My Favorites",
      "recently_updated": "Recently Updated",
      "points_of_interest": "Points of Interest",
      "view_all": "view all"
    },
    "places": {
      "title": "Places"
    },
    "my_places": {
      "title": "My Places",
      "favorites": "Favorites"
    }
  },
  "social": {
    "home": {
      "title": "Places Overview",
      "description": "description",
      "image": "image",
      "site": "site",
      "card": "card",
      "creator": "creator"
    },
    "places": {
      "title": "Places",
      "description": "description",
      "image": "image",
      "site": "site",
      "card": "card",
      "creator": "creator"
    },
    "my_places": {
      "title": "My Places",
      "description": "description",
      "image": "image",
      "site": "site",
      "card": "card",
      "creator": "creator"
    },
    "place": {
      "title": "Decentraland Place",
      "description": "This place is awesome",
      "image": "image",
      "site": "site",
      "card": "card",
      "creator": "creator"
    }
  }
}
